umlviz/__init__.py
umlviz/__main__.py
umlviz/cli.py
umlviz/draw.py
umlviz/lexer.py
umlviz/parser.py
umlviz/parsetab.py
umlviz-0.2.1.dist-info/licenses/LICENSE
umlviz-0.2.1.dist-info/METADATA
umlviz-0.2.1.dist-info/WHEEL
umlviz-0.2.1.dist-info/entry_points.txt
umlviz-0.2.1.dist-info/top_level.txt
umlviz-0.2.1.dist-info/RECORD
