Metadata-Version: 2.4
Name: umlviz
Version: 0.2.1
Summary: A CLI to generate a unified modeling language diagrem from programming language based domain-specific language. 
Author-email: Jeff Caffrey-Hill <jeff@caffreyhill.com>
License-Expression: MIT
Keywords: UML
Classifier: Development Status :: 4 - Beta
Classifier: Intended Audience :: Developers
License-File: LICENSE
Requires-Dist: ply
Requires-Dist: graphviz
Dynamic: license-file
